plain/upgrade/CHANGELOG.md
plain/upgrade/README.md
plain/upgrade/__init__.py
plain/upgrade/cli.py
plain_upgrade-0.3.1.dist-info/METADATA
plain_upgrade-0.3.1.dist-info/WHEEL
plain_upgrade-0.3.1.dist-info/entry_points.txt
plain_upgrade-0.3.1.dist-info/RECORD
