Metadata-Version: 2.4
Name: plain.upgrade
Version: 0.3.1
Summary: Upgrade Plain packages using AI agents.
Requires-Python: >=3.11
Requires-Dist: ast-grep-cli>=0.38.5
Requires-Dist: click>=8.0.0
